Workbook

Sheet Raw_Data
A1: Item ID | B1: Item Name | C1: Category | D1: Cost Price | E1: Selling Price | F1: Discount % | G1: Final Price | H1: Monthly Units Sold
A2: A1 | B2: Calzone Chunks | C2: Appetizer | D2: 220 | E2: 350 | F2: 10 | G2: =IF(F2>0,E2-(E2*F2/100),E2) -> 315 | H2: 150
A3: A2 | B3: Bihari Rolls | C3: Appetizer | D3: 180 | E3: 280 | F3: 5 | G3: =IF(F3>0,E3-(E3*F3/100),E3) -> 266 | H3: 200
A4: A3 | B4: Cheesy Sticks | C4: Appetizer | D4: 200 | E4: 320 | F4: 0 | G4: =IF(F4>0,E4-(E4*F4/100),E4) -> 320 | H4: 180
A5: A4 | B5: Chicken Wings | C5: Appetizer | D5: 300 | E5: 450 | F5: 10 | G5: =IF(F5>0,E5-(E5*F5/100),E5) -> 405 | H5: 160
A6: A5 | B6: French Fries | C6: Appetizer | D6: 120 | E6: 250 | F6: 0 | G6: =IF(F6>0,E6-(E6*F6/100),E6) -> 250 | H6: 300
A7: P1 | B7: Crown Crust Pizza | C7: Pizza | D7: 550 | E7: 850 | F7: 15 | G7: =IF(F7>0,E7-(E7*F7/100),E7) -> 722.5 | H7: 140
A8: P2 | B8: Chicken Fajita Pizza | C8: Pizza | D8: 600 | E8: 900 | F8: 10 | G8: =IF(F8>0,E8-(E8*F8/100),E8) -> 810 | H8: 160
A9: P3 | B9: Cheese Lovers Pizza | C9: Pizza | D9: 520 | E9: 800 | F9: 5 | G9: =IF(F9>0,E9-(E9*F9/100),E9) -> 760 | H9: 150
A10: P4 | B10: Chicken Tikka Pizza | C10: Pizza | D10: 560 | E10: 850 | F10: 10 | G10: =IF(F10>0,E10-(E10*F10/100),E10) -> 765 | H10: 155
A11: P5 | B11: Malai Tikka Pizza | C11: Pizza | D11: 570 | E11: 850 | F11: 10 | G11: =IF(F11>0,E11-(E11*F11/100),E11) -> 765 | H11: 145
A12: B1 | B12: Reggy Burger | C12: Burger | D12: 280 | E12: 450 | F12: 5 | G12: =IF(F12>0,E12-(E12*F12/100),E12) -> 427.5 | H12: 200
A13: B2 | B13: Bazinga Burger | C13: Burger | D13: 340 | E13: 550 | F13: 10 | G13: =IF(F13>0,E13-(E13*F13/100),E13) -> 495 | H13: 180
... A16: B5 | B16: Cheese Burger | C16: Burger | D16: 300 | E16: 500 | F16: 5 | G16: =IF(F16>0,E16-(E16*F16/100),E16) -> 475 | H16: 190

Sheet Profit_Calculations
A1: Item Name | B1: Final Price | C1: Cost Price | D1: Units | E1: Monthly Revenue | F1: Monthly Cost | G1: Monthly Profit | H1: Profit %
A2: =Raw_Data!B2 -> Calzone Chunks | B2: =Raw_Data!G2 -> 315 | C2: =Raw_Data!D2 -> 220 | D2: =Raw_Data!H2 -> 150 | E2: =B2*D2 -> 47250 | F2: =C2*D2 -> 33000 | G2: =E2-F2 -> 14250 | H2: =IF(F2=0,0,(G2/F2)*100) -> 43.181818
A3: =Raw_Data!B3 -> Bihari Rolls | B3: =Raw_Data!G3 -> 266 | C3: =Raw_Data!D3 -> 180 | D3: =Raw_Data!H3 -> 200 | E3: =B3*D3 -> 53200 | F3: =C3*D3 -> 36000 | G3: =E3-F3 -> 17200 | H3: =IF(F3=0,0,(G3/F3)*100) -> 47.777778
A4: =Raw_Data!B4 -> Cheesy Sticks | B4: =Raw_Data!G4 -> 320 | C4: =Raw_Data!D4 -> 200 | D4: =Raw_Data!H4 -> 180 | E4: =B4*D4 -> 57600 | F4: =C4*D4 -> 36000 | G4: =E4-F4 -> 21600 | H4: =IF(F4=0,0,(G4/F4)*100) -> 60
A5: =Raw_Data!B5 -> Chicken Wings | B5: =Raw_Data!G5 -> 405 | C5: =Raw_Data!D5 -> 300 | D5: =Raw_Data!H5 -> 160 | E5: =B5*D5 -> 64800 | F5: =C5*D5 -> 48000 | G5: =E5-F5 -> 16800 | H5: =IF(F5=0,0,(G5/F5)*100) -> 35
A6: =Raw_Data!B6 -> French Fries | B6: =Raw_Data!G6 -> 250 | C6: =Raw_Data!D6 -> 120 | D6: =Raw_Data!H6 -> 300 | E6: =B6*D6 -> 75000 | F6: =C6*D6 -> 36000 | G6: =E6-F6 -> 39000 | H6: =IF(F6=0,0,(G6/F6)*100) -> 108.33333
A7: =Raw_Data!B7 -> Crown Crust Pizza | B7: =Raw_Data!G7 -> 722.5 | C7: =Raw_Data!D7 -> 550 | D7: =Raw_Data!H7 -> 140 | E7: =B7*D7 -> 101150 | F7: =C7*D7 -> 77000 | G7: =E7-F7 -> 24150 | H7: =IF(F7=0,0,(G7/F7)*100) -> 31.363636
A8: =Raw_Data!B8 -> Chicken Fajita Pizza | B8: =Raw_Data!G8 -> 810 | C8: =Raw_Data!D8 -> 600 | D8: =Raw_Data!H8 -> 160 | E8: =B8*D8 -> 129600 | F8: =C8*D8 -> 96000 | G8: =E8-F8 -> 33600 | H8: =IF(F8=0,0,(G8/F8)*100) -> 35
A9: =Raw_Data!B9 -> Cheese Lovers Pizza | B9: =Raw_Data!G9 -> 760 | C9: =Raw_Data!D9 -> 520 | D9: =Raw_Data!H9 -> 150 | E9: =B9*D9 -> 114000 | F9: =C9*D9 -> 78000 | G9: =E9-F9 -> 36000 | H9: =IF(F9=0,0,(G9/F9)*100) -> 46.153846
A10: =Raw_Data!B10 -> Chicken Tikka Pizza | B10: =Raw_Data!G10 -> 765 | C10: =Raw_Data!D10 -> 560 | D10: =Raw_Data!H10 -> 155 | E10: =B10*D10 -> 118575 | F10: =C10*D10 -> 86800 | G10: =E10-F10 -> 31775 | H10: =IF(F10=0,0,(G10/F10)*100) -> 36.607143
A11: =Raw_Data!B11 -> Malai Tikka Pizza | B11: =Raw_Data!G11 -> 765 | C11: =Raw_Data!D11 -> 570 | D11: =Raw_Data!H11 -> 145 | E11: =B11*D11 -> 110925 | F11: =C11*D11 -> 82650 | G11: =E11-F11 -> 28275 | H11: =IF(F11=0,0,(G11/F11)*100) -> 34.210526
A12: =Raw_Data!B12 -> Reggy Burger | B12: =Raw_Data!G12 -> 427.5 | C12: =Raw_Data!D12 -> 280 | D12: =Raw_Data!H12 -> 200 | E12: =B12*D12 -> 85500 | F12: =C12*D12 -> 56000 | G12: =E12-F12 -> 29500 | H12: =IF(F12=0,0,(G12/F12)*100) -> 52.678571
A13: =Raw_Data!B13 -> Bazinga Burger | B13: =Raw_Data!G13 -> 495 | C13: =Raw_Data!D13 -> 340 | D13: =Raw_Data!H13 -> 180 | E13: =B13*D13 -> 89100 | F13: =C13*D13 -> 61200 | G13: =E13-F13 -> 27900 | H13: =IF(F13=0,0,(G13/F13)*100) -> 45.588235
... A16: =Raw_Data!B16 -> Cheese Burger | B16: =Raw_Data!G16 -> 475 | C16: =Raw_Data!D16 -> 300 | D16: =Raw_Data!H16 -> 190 | E16: =B16*D16 -> 90250 | F16: =C16*D16 -> 57000 | G16: =E16-F16 -> 33250 | H16: =IF(F16=0,0,(G16/F16)*100) -> 58.333333

Sheet Summary
A1: Metric | B1: Value
A2: Average Selling Price | B2: =AVERAGE(Raw_Data!G2:G16) -> 517.4
A3: Average Cost Price | B3: =AVERAGE(Raw_Data!D2:D16) -> 359.33333
A4: Total Monthly Profit | B4: =SUM(Profit_Calculations!G2:G16) -> 414050
A5: Total Yearly Profit | B5: =B4*12 -> 4968600

Sheet Dashboard
A1: Month | B1: Profit/Loss
A2: Jan | B2: 420000
A3: Feb | B3: 380000
A4: Mar | B4: -55000
A5: Apr | B5: 460000
A6: May | B6: 500000
A7: Jun | B7: -72000
A8: Jul | B8: 610000
A9: Aug | B9: 580000
A10: Sep | B10: 450000
A11: Oct | B11: -90000
A12: Nov | B12: 640000
A13: Dec | B13: 700000
